agents/__init__.py
agents/agents.py
agents/ollama_framework.py
agents/providers.py
agents/utils.py
lagents-0.1.1.dist-info/licenses/LICENSE
lagents-0.1.1.dist-info/METADATA
lagents-0.1.1.dist-info/WHEEL
lagents-0.1.1.dist-info/top_level.txt
lagents-0.1.1.dist-info/RECORD
