Metadata-Version: 2.4
Name: lagents
Version: 0.1.1
Summary: L'Agent - Minimal experimental framework for building agents with local LLM deployments. Zero bloat, maximum simplicity.
Home-page: https://github.com/BenevolentJoker-JohnL/agents
Author: BenevolentJoker
Author-email: benevolentjoker@example.com
Project-URL: Bug Reports, https://github.com/BenevolentJoker-JohnL/agents/issues
Project-URL: Source, https://github.com/BenevolentJoker-JohnL/agents
Project-URL: Documentation, https://github.com/BenevolentJoker-JohnL/agents#readme
Keywords: llm agents ollama local minimal framework llama vllm lagent
Classifier: Development Status :: 3 - Alpha
Classifier: Intended Audience :: Developers
Classifier: Topic :: Software Development :: Libraries :: Python Modules
Classifier: Topic :: Scientific/Engineering :: Artificial Intelligence
Classifier: License :: OSI Approved :: MIT License
Classifier: Programming Language :: Python :: 3
Classifier: Programming Language :: Python :: 3.8
Classifier: Programming Language :: Python :: 3.9
Classifier: Programming Language :: Python :: 3.10
Classifier: Programming Language :: Python :: 3.11
Classifier: Programming Language :: Python :: 3.12
Requires-Python: >=3.8
License-File: LICENSE
Requires-Dist: aiohttp>=3.8.0
Requires-Dist: numpy>=1.20.0
Provides-Extra: distributed
Requires-Dist: sollol>=0.1.0; extra == "distributed"
Provides-Extra: dev
Requires-Dist: pytest>=7.0.0; extra == "dev"
Requires-Dist: pytest-asyncio>=0.20.0; extra == "dev"
Requires-Dist: black>=22.0.0; extra == "dev"
Requires-Dist: isort>=5.10.0; extra == "dev"
Requires-Dist: mypy>=0.950; extra == "dev"
Dynamic: author
Dynamic: author-email
Dynamic: classifier
Dynamic: description
Dynamic: description-content-type
Dynamic: home-page
Dynamic: keywords
Dynamic: license-file
Dynamic: project-url
Dynamic: provides-extra
Dynamic: requires-dist
Dynamic: requires-python
Dynamic: summary
